odoo/addons/mrp_weighing/README.rst
odoo/addons/mrp_weighing/__init__.py
odoo/addons/mrp_weighing/__manifest__.py
odoo/addons/mrp_weighing/i18n/mrp_weighing.pot
odoo/addons/mrp_weighing/models/__init__.py
odoo/addons/mrp_weighing/models/mrp_production.py
odoo/addons/mrp_weighing/models/stock_move.py
odoo/addons/mrp_weighing/models/stock_move_line.py
odoo/addons/mrp_weighing/readme/CONTRIBUTORS.md
odoo/addons/mrp_weighing/readme/DESCRIPTION.md
odoo/addons/mrp_weighing/static/description/icon.png
odoo/addons/mrp_weighing/static/description/index.html
odoo/addons/mrp_weighing/views/mrp_production_view.xml
odoo/addons/mrp_weighing/wizards/__init__.py
odoo/addons/mrp_weighing/wizards/weigh_operation_selection.py
odoo/addons/mrp_weighing/wizards/weighing_wizard.py
odoo_addon_mrp_weighing-15.0.1.0.1.dist-info/METADATA
odoo_addon_mrp_weighing-15.0.1.0.1.dist-info/WHEEL
odoo_addon_mrp_weighing-15.0.1.0.1.dist-info/top_level.txt
odoo_addon_mrp_weighing-15.0.1.0.1.dist-info/RECORD
